main/__init__.py
main/pGp.py
PyGetPic-0.0.1.dist-info/LICENSE
PyGetPic-0.0.1.dist-info/METADATA
PyGetPic-0.0.1.dist-info/WHEEL
PyGetPic-0.0.1.dist-info/top_level.txt
PyGetPic-0.0.1.dist-info/RECORD
