Metadata-Version: 2.1
Name: PyGetPic
Version: 0.0.1
Summary: A small package for getting random images :)
Home-page: https://github.com/N0t-Eth1ca1-Hac4r/pygetpic
Author: D4C
Author-email: d4c@dfourc.space
License: UNKNOWN
Platform: UNKNOWN
Classifier: Programming Language :: Python :: 3
Classifier: License :: OSI Approved :: MIT License
Classifier: Operating System :: OS Independent
Requires-Python: >=3.6
